boklib/__init__.py
boklib-1.1.dist-info/LICENSE
boklib-1.1.dist-info/METADATA
boklib-1.1.dist-info/WHEEL
boklib-1.1.dist-info/top_level.txt
boklib-1.1.dist-info/RECORD
