Metadata-Version: 2.1
Name: boklib
Version: 1.1
Summary: parsing a bank of korea api
Home-page: https://github.com/neur0hak/boklib
Author: neur0hak
Author-email: xxx9981@gmail.com
License: UNKNOWN
Platform: UNKNOWN
Classifier: Programming Language :: Python
Classifier: License :: OSI Approved :: MIT License
Classifier: Operating System :: OS Independent
Requires-Dist: requests
